setup.cfg
setup.py
falcon_jwt_checker/__init__.py
falcon_jwt_checker/falcon_jwt_checker.py
falcon_jwt_checker.egg-info/PKG-INFO
falcon_jwt_checker.egg-info/SOURCES.txt
falcon_jwt_checker.egg-info/dependency_links.txt
falcon_jwt_checker.egg-info/requires.txt
falcon_jwt_checker.egg-info/top_level.txt