Metadata-Version: 1.1
Name: falcon-jwt-checker
Version: 0.1.2
Summary: Falcon middleware to validate JWTs on routes.
Home-page: https://github.com/jhildreth/falcon-jwt-checker
Author: Justin Hildreth
Author-email: it@justinhildreth.com
License: MIT
Download-URL: https://github.com/jhildreth/falcon-jwt-checker/tarball/0.1.2
Keywords: jwt,falcon
Platform: UNKNOWN
Classifier: Development Status :: 3 - Alpha
Classifier: Intended Audience :: Developers
Classifier: Natural Language :: English
Classifier: License :: OSI Approved :: MIT License
Classifier: Programming Language :: Python :: 3
